{
  "id": "Mission 1",
  "description": "Mission 1: Expand through your solar system",
  "demoMode": false,
  "universeMaxX": 1000,
  "universeMaxY": 1000,
  "starMaxOrbit": 40.0,
  "planetOrbit": 2.0,
  "numberOfStars": 1,
  "numberOfRaces": 1,
  "nextGlobalID": 1001,
  "secondPlayer": false,
  "playerTurns": [
    5,
    5
  ],
  "turn": 1,
  "stars": {
    "0": {
      "uid": 0,
      "numberOfPlanets": 5,
      "loc": {
        "level": 4,
        "uidRef": -1,
        "x": 410.0,
        "y": 710.0,
        "t": -1.0,
        "r": -1.0,
        "sx": -1,
        "sy": -1
      },
      "name": "Upsilon",
      "starUidPatrolPoints": [
        0,
        1
      ],
      "starUidPlanets": [
        0,
        1,
        2,
        3,
        4
      ],
      "starUidShips": []
    }
  },
  "planets": {
    "0": {
      "uid": 0,
      "sid": 0,
      "uidStar": 0,
      "loc": {
        "level": 3,
        "uidRef": 0,
        "x": 7.1937537,
        "y": 0.29984215,
        "t": 0.041656792,
        "r": 7.2,
        "sx": -1,
        "sy": -1
      },
      "height": 3,
      "idxtype": 5,
      "landedUidShips": [
        1000
      ],
      "name": "Dawn",
      "orbitUidShips": [],
      "planetPopulation": 100,
      "planetUidRaces": [
        0
      ],
      "sectors": [
        {
          "uidPlanet": 0,
          "i": 0,
          "maxPopulation": 100,
          "population": 0,
          "revenue": 0,
          "type": 6,
          "typeSymbol": "#",
          "uidSectorOwner": -1,
          "x": 0,
          "y": 0
        },
        {
          "uidPlanet": 0,
          "i": 1,
          "maxPopulation": 100,
          "population": 0,
          "revenue": 0,
          "type": 6,
          "typeSymbol": "#",
          "uidSectorOwner": -1,
          "x": 1,
          "y": 0
        },
        {
          "uidPlanet": 0,
          "i": 2,
          "maxPopulation": 100,
          "population": 0,
          "revenue": 0,
          "type": 6,
          "typeSymbol": "#",
          "uidSectorOwner": -1,
          "x": 2,
          "y": 0
        },
        {
          "uidPlanet": 0,
          "i": 3,
          "maxPopulation": 200,
          "population": 0,
          "revenue": 2,
          "type": 7,
          "typeSymbol": "x",
          "uidSectorOwner": -1,
          "x": 3,
          "y": 0
        },
        {
          "uidPlanet": 0,
          "i": 4,
          "maxPopulation": 100,
          "population": 0,
          "revenue": 0,
          "type": 6,
          "typeSymbol": "#",
          "uidSectorOwner": -1,
          "x": 4,
          "y": 0
        },
        {
          "uidPlanet": 0,
          "i": 5,
          "maxPopulation": 100,
          "population": 0,
          "revenue": 0,
          "type": 6,
          "typeSymbol": "#",
          "uidSectorOwner": -1,
          "x": 5,
          "y": 0
        },
        {
          "uidPlanet": 0,
          "i": 6,
          "maxPopulation": 100,
          "population": 0,
          "revenue": 0,
          "type": 6,
          "typeSymbol": "#",
          "uidSectorOwner": -1,
          "x": 0,
          "y": 1
        },
        {
          "uidPlanet": 0,
          "i": 7,
          "maxPopulation": 100,
          "population": 0,
          "revenue": 0,
          "type": 6,
          "typeSymbol": "#",
          "uidSectorOwner": -1,
          "x": 1,
          "y": 1
        },
        {
          "uidPlanet": 0,
          "i": 8,
          "maxPopulation": 100,
          "population": 0,
          "revenue": 0,
          "type": 6,
          "typeSymbol": "#",
          "uidSectorOwner": -1,
          "x": 2,
          "y": 1
        },
        {
          "uidPlanet": 0,
          "i": 9,
          "maxPopulation": 100,
          "population": 100,
          "revenue": 0,
          "type": 6,
          "typeSymbol": "#",
          "uidSectorOwner": 0,
          "x": 3,
          "y": 1
        },
        {
          "uidPlanet": 0,
          "i": 10,
          "maxPopulation": 100,
          "population": 0,
          "revenue": 0,
          "type": 6,
          "typeSymbol": "#",
          "uidSectorOwner": -1,
          "x": 4,
          "y": 1
        },
        {
          "uidPlanet": 0,
          "i": 11,
          "maxPopulation": 100,
          "population": 0,
          "revenue": 0,
          "type": 6,
          "typeSymbol": "#",
          "uidSectorOwner": -1,
          "x": 5,
          "y": 1
        },
        {
          "uidPlanet": 0,
          "i": 12,
          "maxPopulation": 100,
          "population": 0,
          "revenue": 0,
          "type": 6,
          "typeSymbol": "#",
          "uidSectorOwner": -1,
          "x": 0,
          "y": 2
        },
        {
          "uidPlanet": 0,
          "i": 13,
          "maxPopulation": 100,
          "population": 0,
          "revenue": 0,
          "type": 6,
          "typeSymbol": "#",
          "uidSectorOwner": -1,
          "x": 1,
          "y": 2
        },
        {
          "uidPlanet": 0,
          "i": 14,
          "maxPopulation": 100,
          "population": 0,
          "revenue": 0,
          "type": 6,
          "typeSymbol": "#",
          "uidSectorOwner": -1,
          "x": 2,
          "y": 2
        },
        {
          "uidPlanet": 0,
          "i": 15,
          "maxPopulation": 100,
          "population": 0,
          "revenue": 0,
          "type": 6,
          "typeSymbol": "#",
          "uidSectorOwner": -1,
          "x": 3,
          "y": 2
        },
        {
          "uidPlanet": 0,
          "i": 16,
          "maxPopulation": 100,
          "population": 0,
          "revenue": 0,
          "type": 6,
          "typeSymbol": "#",
          "uidSectorOwner": -1,
          "x": 4,
          "y": 2
        },
        {
          "uidPlanet": 0,
          "i": 17,
          "maxPopulation": 100,
          "population": 0,
          "revenue": 0,
          "type": 6,
          "typeSymbol": "#",
          "uidSectorOwner": -1,
          "x": 5,
          "y": 2
        }
      ],
      "type": "Iceball",
      "width": 6
    },
    "1": {
      "uid": 1,
      "sid": 1,
      "uidStar": 0,
      "loc": {
        "level": 3,
        "uidRef": 0,
        "x": -14.375738,
        "y": 0.83555436,
        "t": 3.0835354,
        "r": 14.4,
        "sx": -1,
        "sy": -1
      },
      "height": 4,
      "idxtype": 2,
      "landedUidShips": [],
      "name": "Parvati",
      "orbitUidShips": [],
      "planetPopulation": 0,
      "planetUidRaces": [],
      "sectors": [
        {
          "uidPlanet": 1,
          "i": 0,
          "maxPopulation": 1000,
          "population": 0,
          "revenue": 1,
          "type": 0,
          "typeSymbol": "~",
          "uidSectorOwner": -1,
          "x": 0,
          "y": 0
        },
        {
          "uidPlanet": 1,
          "i": 1,
          "maxPopulation": 1000,
          "population": 0,
          "revenue": 1,
          "type": 0,
          "typeSymbol": "~",
          "uidSectorOwner": -1,
          "x": 1,
          "y": 0
        },
        {
          "uidPlanet": 1,
          "i": 2,
          "maxPopulation": 1000,
          "population": 0,
          "revenue": 1,
          "type": 0,
          "typeSymbol": "~",
          "uidSectorOwner": -1,
          "x": 2,
          "y": 0
        },
        {
          "uidPlanet": 1,
          "i": 3,
          "maxPopulation": 1000,
          "population": 0,
          "revenue": 1,
          "type": 0,
          "typeSymbol": "~",
          "uidSectorOwner": -1,
          "x": 3,
          "y": 0
        },
        {
          "uidPlanet": 1,
          "i": 4,
          "maxPopulation": 1000,
          "population": 0,
          "revenue": 1,
          "type": 0,
          "typeSymbol": "~",
          "uidSectorOwner": -1,
          "x": 4,
          "y": 0
        },
        {
          "uidPlanet": 1,
          "i": 5,
          "maxPopulation": 1000,
          "population": 0,
          "revenue": 1,
          "type": 0,
          "typeSymbol": "~",
          "uidSectorOwner": -1,
          "x": 5,
          "y": 0
        },
        {
          "uidPlanet": 1,
          "i": 6,
          "maxPopulation": 1000,
          "population": 0,
          "revenue": 1,
          "type": 0,
          "typeSymbol": "~",
          "uidSectorOwner": -1,
          "x": 6,
          "y": 0
        },
        {
          "uidPlanet": 1,
          "i": 7,
          "maxPopulation": 1000,
          "population": 0,
          "revenue": 1,
          "type": 0,
          "typeSymbol": "~",
          "uidSectorOwner": -1,
          "x": 7,
          "y": 0
        },
        {
          "uidPlanet": 1,
          "i": 8,
          "maxPopulation": 1000,
          "population": 0,
          "revenue": 1,
          "type": 0,
          "typeSymbol": "~",
          "uidSectorOwner": -1,
          "x": 0,
          "y": 1
        },
        {
          "uidPlanet": 1,
          "i": 9,
          "maxPopulation": 1000,
          "population": 0,
          "revenue": 1,
          "type": 0,
          "typeSymbol": "~",
          "uidSectorOwner": -1,
          "x": 1,
          "y": 1
        },
        {
          "uidPlanet": 1,
          "i": 10,
          "maxPopulation": 800,
          "population": 0,
          "revenue": 2,
          "type": 4,
          "typeSymbol": "^",
          "uidSectorOwner": -1,
          "x": 2,
          "y": 1
        },
        {
          "uidPlanet": 1,
          "i": 11,
          "maxPopulation": 1000,
          "population": 0,
          "revenue": 1,
          "type": 0,
          "typeSymbol": "~",
          "uidSectorOwner": -1,
          "x": 3,
          "y": 1
        },
        {
          "uidPlanet": 1,
          "i": 12,
          "maxPopulation": 1000,
          "population": 0,
          "revenue": 1,
          "type": 0,
          "typeSymbol": "~",
          "uidSectorOwner": -1,
          "x": 4,
          "y": 1
        },
        {
          "uidPlanet": 1,
          "i": 13,
          "maxPopulation": 1000,
          "population": 0,
          "revenue": 1,
          "type": 0,
          "typeSymbol": "~",
          "uidSectorOwner": -1,
          "x": 5,
          "y": 1
        },
        {
          "uidPlanet": 1,
          "i": 14,
          "maxPopulation": 1000,
          "population": 0,
          "revenue": 1,
          "type": 0,
          "typeSymbol": "~",
          "uidSectorOwner": -1,
          "x": 6,
          "y": 1
        },
        {
          "uidPlanet": 1,
          "i": 15,
          "maxPopulation": 1000,
          "population": 0,
          "revenue": 1,
          "type": 0,
          "typeSymbol": "~",
          "uidSectorOwner": -1,
          "x": 7,
          "y": 1
        },
        {
          "uidPlanet": 1,
          "i": 16,
          "maxPopulation": 1000,
          "population": 0,
          "revenue": 1,
          "type": 0,
          "typeSymbol": "~",
          "uidSectorOwner": -1,
          "x": 0,
          "y": 2
        },
        {
          "uidPlanet": 1,
          "i": 17,
          "maxPopulation": 1000,
          "population": 0,
          "revenue": 1,
          "type": 0,
          "typeSymbol": "~",
          "uidSectorOwner": -1,
          "x": 1,
          "y": 2
        },
        {
          "uidPlanet": 1,
          "i": 18,
          "maxPopulation": 1000,
          "population": 0,
          "revenue": 1,
          "type": 0,
          "typeSymbol": "~",
          "uidSectorOwner": -1,
          "x": 2,
          "y": 2
        },
        {
          "uidPlanet": 1,
          "i": 19,
          "maxPopulation": 800,
          "population": 0,
          "revenue": 2,
          "type": 4,
          "typeSymbol": "^",
          "uidSectorOwner": -1,
          "x": 3,
          "y": 2
        },
        {
          "uidPlanet": 1,
          "i": 20,
          "maxPopulation": 1000,
          "population": 0,
          "revenue": 1,
          "type": 0,
          "typeSymbol": "~",
          "uidSectorOwner": -1,
          "x": 4,
          "y": 2
        },
        {
          "uidPlanet": 1,
          "i": 21,
          "maxPopulation": 1000,
          "population": 0,
          "revenue": 1,
          "type": 0,
          "typeSymbol": "~",
          "uidSectorOwner": -1,
          "x": 5,
          "y": 2
        },
        {
          "uidPlanet": 1,
          "i": 22,
          "maxPopulation": 1000,
          "population": 0,
          "revenue": 1,
          "type": 0,
          "typeSymbol": "~",
          "uidSectorOwner": -1,
          "x": 6,
          "y": 2
        },
        {
          "uidPlanet": 1,
          "i": 23,
          "maxPopulation": 1000,
          "population": 0,
          "revenue": 1,
          "type": 0,
          "typeSymbol": "~",
          "uidSectorOwner": -1,
          "x": 7,
          "y": 2
        },
        {
          "uidPlanet": 1,
          "i": 24,
          "maxPopulation": 1000,
          "population": 0,
          "revenue": 1,
          "type": 0,
          "typeSymbol": "~",
          "uidSectorOwner": -1,
          "x": 0,
          "y": 3
        },
        {
          "uidPlanet": 1,
          "i": 25,
          "maxPopulation": 1000,
          "population": 0,
          "revenue": 1,
          "type": 0,
          "typeSymbol": "~",
          "uidSectorOwner": -1,
          "x": 1,
          "y": 3
        },
        {
          "uidPlanet": 1,
          "i": 26,
          "maxPopulation": 800,
          "population": 0,
          "revenue": 2,
          "type": 4,
          "typeSymbol": "^",
          "uidSectorOwner": -1,
          "x": 2,
          "y": 3
        },
        {
          "uidPlanet": 1,
          "i": 27,
          "maxPopulation": 1000,
          "population": 0,
          "revenue": 1,
          "type": 0,
          "typeSymbol": "~",
          "uidSectorOwner": -1,
          "x": 3,
          "y": 3
        },
        {
          "uidPlanet": 1,
          "i": 28,
          "maxPopulation": 1000,
          "population": 0,
          "revenue": 1,
          "type": 0,
          "typeSymbol": "~",
          "uidSectorOwner": -1,
          "x": 4,
          "y": 3
        },
        {
          "uidPlanet": 1,
          "i": 29,
          "maxPopulation": 1000,
          "population": 0,
          "revenue": 1,
          "type": 0,
          "typeSymbol": "~",
          "uidSectorOwner": -1,
          "x": 5,
          "y": 3
        },
        {
          "uidPlanet": 1,
          "i": 30,
          "maxPopulation": 1000,
          "population": 0,
          "revenue": 1,
          "type": 0,
          "typeSymbol": "~",
          "uidSectorOwner": -1,
          "x": 6,
          "y": 3
        },
        {
          "uidPlanet": 1,
          "i": 31,
          "maxPopulation": 1000,
          "population": 0,
          "revenue": 1,
          "type": 0,
          "typeSymbol": "~",
          "uidSectorOwner": -1,
          "x": 7,
          "y": 3
        }
      ],
      "type": "Water",
      "width": 8
    },
    "2": {
      "uid": 2,
      "sid": 2,
      "uidStar": 0,
      "loc": {
        "level": 3,
        "uidRef": 0,
        "x": 13.541613,
        "y": 16.828093,
        "t": 0.89319444,
        "r": 21.599998,
        "sx": -1,
        "sy": -1
      },
      "height": 3,
      "idxtype": 5,
      "landedUidShips": [],
      "name": "Medea",
      "orbitUidShips": [],
      "planetPopulation": 0,
      "planetUidRaces": [],
      "sectors": [
        {
          "uidPlanet": 2,
          "i": 0,
          "maxPopulation": 200,
          "population": 0,
          "revenue": 2,
          "type": 7,
          "typeSymbol": "x",
          "uidSectorOwner": -1,
          "x": 0,
          "y": 0
        },
        {
          "uidPlanet": 2,
          "i": 1,
          "maxPopulation": 100,
          "population": 0,
          "revenue": 0,
          "type": 6,
          "typeSymbol": "#",
          "uidSectorOwner": -1,
          "x": 1,
          "y": 0
        },
        {
          "uidPlanet": 2,
          "i": 2,
          "maxPopulation": 100,
          "population": 0,
          "revenue": 0,
          "type": 6,
          "typeSymbol": "#",
          "uidSectorOwner": -1,
          "x": 2,
          "y": 0
        },
        {
          "uidPlanet": 2,
          "i": 3,
          "maxPopulation": 100,
          "population": 0,
          "revenue": 0,
          "type": 6,
          "typeSymbol": "#",
          "uidSectorOwner": -1,
          "x": 3,
          "y": 0
        },
        {
          "uidPlanet": 2,
          "i": 4,
          "maxPopulation": 100,
          "population": 0,
          "revenue": 0,
          "type": 6,
          "typeSymbol": "#",
          "uidSectorOwner": -1,
          "x": 4,
          "y": 0
        },
        {
          "uidPlanet": 2,
          "i": 5,
          "maxPopulation": 100,
          "population": 0,
          "revenue": 0,
          "type": 6,
          "typeSymbol": "#",
          "uidSectorOwner": -1,
          "x": 5,
          "y": 0
        },
        {
          "uidPlanet": 2,
          "i": 6,
          "maxPopulation": 100,
          "population": 0,
          "revenue": 0,
          "type": 6,
          "typeSymbol": "#",
          "uidSectorOwner": -1,
          "x": 0,
          "y": 1
        },
        {
          "uidPlanet": 2,
          "i": 7,
          "maxPopulation": 100,
          "population": 0,
          "revenue": 0,
          "type": 6,
          "typeSymbol": "#",
          "uidSectorOwner": -1,
          "x": 1,
          "y": 1
        },
        {
          "uidPlanet": 2,
          "i": 8,
          "maxPopulation": 100,
          "population": 0,
          "revenue": 0,
          "type": 6,
          "typeSymbol": "#",
          "uidSectorOwner": -1,
          "x": 2,
          "y": 1
        },
        {
          "uidPlanet": 2,
          "i": 9,
          "maxPopulation": 200,
          "population": 0,
          "revenue": 2,
          "type": 7,
          "typeSymbol": "x",
          "uidSectorOwner": -1,
          "x": 3,
          "y": 1
        },
        {
          "uidPlanet": 2,
          "i": 10,
          "maxPopulation": 100,
          "population": 0,
          "revenue": 0,
          "type": 6,
          "typeSymbol": "#",
          "uidSectorOwner": -1,
          "x": 4,
          "y": 1
        },
        {
          "uidPlanet": 2,
          "i": 11,
          "maxPopulation": 100,
          "population": 0,
          "revenue": 0,
          "type": 6,
          "typeSymbol": "#",
          "uidSectorOwner": -1,
          "x": 5,
          "y": 1
        },
        {
          "uidPlanet": 2,
          "i": 12,
          "maxPopulation": 100,
          "population": 0,
          "revenue": 0,
          "type": 6,
          "typeSymbol": "#",
          "uidSectorOwner": -1,
          "x": 0,
          "y": 2
        },
        {
          "uidPlanet": 2,
          "i": 13,
          "maxPopulation": 100,
          "population": 0,
          "revenue": 0,
          "type": 6,
          "typeSymbol": "#",
          "uidSectorOwner": -1,
          "x": 1,
          "y": 2
        },
        {
          "uidPlanet": 2,
          "i": 14,
          "maxPopulation": 200,
          "population": 0,
          "revenue": 2,
          "type": 7,
          "typeSymbol": "x",
          "uidSectorOwner": -1,
          "x": 2,
          "y": 2
        },
        {
          "uidPlanet": 2,
          "i": 15,
          "maxPopulation": 100,
          "population": 0,
          "revenue": 0,
          "type": 6,
          "typeSymbol": "#",
          "uidSectorOwner": -1,
          "x": 3,
          "y": 2
        },
        {
          "uidPlanet": 2,
          "i": 16,
          "maxPopulation": 100,
          "population": 0,
          "revenue": 0,
          "type": 6,
          "typeSymbol": "#",
          "uidSectorOwner": -1,
          "x": 4,
          "y": 2
        },
        {
          "uidPlanet": 2,
          "i": 17,
          "maxPopulation": 100,
          "population": 0,
          "revenue": 0,
          "type": 6,
          "typeSymbol": "#",
          "uidSectorOwner": -1,
          "x": 5,
          "y": 2
        }
      ],
      "type": "Iceball",
      "width": 6
    },
    "3": {
      "uid": 3,
      "sid": 3,
      "uidStar": 0,
      "loc": {
        "level": 3,
        "uidRef": 0,
        "x": 16.807407,
        "y": 23.386984,
        "t": 0.947653,
        "r": 28.8,
        "sx": -1,
        "sy": -1
      },
      "height": 4,
      "idxtype": 6,
      "landedUidShips": [],
      "name": "Argos",
      "orbitUidShips": [],
      "planetPopulation": 0,
      "planetUidRaces": [],
      "sectors": [
        {
          "uidPlanet": 3,
          "i": 0,
          "maxPopulation": 200,
          "population": 0,
          "revenue": 2,
          "type": 7,
          "typeSymbol": "x",
          "uidSectorOwner": -1,
          "x": 0,
          "y": 0
        },
        {
          "uidPlanet": 3,
          "i": 1,
          "maxPopulation": 500,
          "population": 0,
          "revenue": 1,
          "type": 3,
          "typeSymbol": "-",
          "uidSectorOwner": -1,
          "x": 1,
          "y": 0
        },
        {
          "uidPlanet": 3,
          "i": 2,
          "maxPopulation": 800,
          "population": 0,
          "revenue": 2,
          "type": 4,
          "typeSymbol": "^",
          "uidSectorOwner": -1,
          "x": 2,
          "y": 0
        },
        {
          "uidPlanet": 3,
          "i": 3,
          "maxPopulation": 800,
          "population": 0,
          "revenue": 2,
          "type": 4,
          "typeSymbol": "^",
          "uidSectorOwner": -1,
          "x": 3,
          "y": 0
        },
        {
          "uidPlanet": 3,
          "i": 4,
          "maxPopulation": 500,
          "population": 0,
          "revenue": 1,
          "type": 3,
          "typeSymbol": "-",
          "uidSectorOwner": -1,
          "x": 4,
          "y": 0
        },
        {
          "uidPlanet": 3,
          "i": 5,
          "maxPopulation": 800,
          "population": 0,
          "revenue": 2,
          "type": 4,
          "typeSymbol": "^",
          "uidSectorOwner": -1,
          "x": 5,
          "y": 0
        },
        {
          "uidPlanet": 3,
          "i": 6,
          "maxPopulation": 500,
          "population": 0,
          "revenue": 1,
          "type": 3,
          "typeSymbol": "-",
          "uidSectorOwner": -1,
          "x": 6,
          "y": 0
        },
        {
          "uidPlanet": 3,
          "i": 7,
          "maxPopulation": 200,
          "population": 0,
          "revenue": 2,
          "type": 7,
          "typeSymbol": "x",
          "uidSectorOwner": -1,
          "x": 7,
          "y": 0
        },
        {
          "uidPlanet": 3,
          "i": 8,
          "maxPopulation": 500,
          "population": 0,
          "revenue": 1,
          "type": 3,
          "typeSymbol": "-",
          "uidSectorOwner": -1,
          "x": 0,
          "y": 1
        },
        {
          "uidPlanet": 3,
          "i": 9,
          "maxPopulation": 100,
          "population": 0,
          "revenue": 0,
          "type": 6,
          "typeSymbol": "#",
          "uidSectorOwner": -1,
          "x": 1,
          "y": 1
        },
        {
          "uidPlanet": 3,
          "i": 10,
          "maxPopulation": 200,
          "population": 0,
          "revenue": 2,
          "type": 7,
          "typeSymbol": "x",
          "uidSectorOwner": -1,
          "x": 2,
          "y": 1
        },
        {
          "uidPlanet": 3,
          "i": 11,
          "maxPopulation": 500,
          "population": 0,
          "revenue": 1,
          "type": 3,
          "typeSymbol": "-",
          "uidSectorOwner": -1,
          "x": 3,
          "y": 1
        },
        {
          "uidPlanet": 3,
          "i": 12,
          "maxPopulation": 100,
          "population": 0,
          "revenue": 0,
          "type": 6,
          "typeSymbol": "#",
          "uidSectorOwner": -1,
          "x": 4,
          "y": 1
        },
        {
          "uidPlanet": 3,
          "i": 13,
          "maxPopulation": 500,
          "population": 0,
          "revenue": 1,
          "type": 3,
          "typeSymbol": "-",
          "uidSectorOwner": -1,
          "x": 5,
          "y": 1
        },
        {
          "uidPlanet": 3,
          "i": 14,
          "maxPopulation": 500,
          "population": 0,
          "revenue": 1,
          "type": 3,
          "typeSymbol": "-",
          "uidSectorOwner": -1,
          "x": 6,
          "y": 1
        },
        {
          "uidPlanet": 3,
          "i": 15,
          "maxPopulation": 2000,
          "population": 0,
          "revenue": 2,
          "type": 1,
          "typeSymbol": ".",
          "uidSectorOwner": -1,
          "x": 7,
          "y": 1
        },
        {
          "uidPlanet": 3,
          "i": 16,
          "maxPopulation": 800,
          "population": 0,
          "revenue": 2,
          "type": 4,
          "typeSymbol": "^",
          "uidSectorOwner": -1,
          "x": 0,
          "y": 2
        },
        {
          "uidPlanet": 3,
          "i": 17,
          "maxPopulation": 500,
          "population": 0,
          "revenue": 1,
          "type": 3,
          "typeSymbol": "-",
          "uidSectorOwner": -1,
          "x": 1,
          "y": 2
        },
        {
          "uidPlanet": 3,
          "i": 18,
          "maxPopulation": 2000,
          "population": 0,
          "revenue": 2,
          "type": 1,
          "typeSymbol": ".",
          "uidSectorOwner": -1,
          "x": 2,
          "y": 2
        },
        {
          "uidPlanet": 3,
          "i": 19,
          "maxPopulation": 800,
          "population": 0,
          "revenue": 2,
          "type": 4,
          "typeSymbol": "^",
          "uidSectorOwner": -1,
          "x": 3,
          "y": 2
        },
        {
          "uidPlanet": 3,
          "i": 20,
          "maxPopulation": 500,
          "population": 0,
          "revenue": 1,
          "type": 3,
          "typeSymbol": "-",
          "uidSectorOwner": -1,
          "x": 4,
          "y": 2
        },
        {
          "uidPlanet": 3,
          "i": 21,
          "maxPopulation": 100,
          "population": 0,
          "revenue": 0,
          "type": 6,
          "typeSymbol": "#",
          "uidSectorOwner": -1,
          "x": 5,
          "y": 2
        },
        {
          "uidPlanet": 3,
          "i": 22,
          "maxPopulation": 800,
          "population": 0,
          "revenue": 2,
          "type": 4,
          "typeSymbol": "^",
          "uidSectorOwner": -1,
          "x": 6,
          "y": 2
        },
        {
          "uidPlanet": 3,
          "i": 23,
          "maxPopulation": 200,
          "population": 0,
          "revenue": 2,
          "type": 7,
          "typeSymbol": "x",
          "uidSectorOwner": -1,
          "x": 7,
          "y": 2
        },
        {
          "uidPlanet": 3,
          "i": 24,
          "maxPopulation": 800,
          "population": 0,
          "revenue": 2,
          "type": 4,
          "typeSymbol": "^",
          "uidSectorOwner": -1,
          "x": 0,
          "y": 3
        },
        {
          "uidPlanet": 3,
          "i": 25,
          "maxPopulation": 500,
          "population": 0,
          "revenue": 1,
          "type": 3,
          "typeSymbol": "-",
          "uidSectorOwner": -1,
          "x": 1,
          "y": 3
        },
        {
          "uidPlanet": 3,
          "i": 26,
          "maxPopulation": 500,
          "population": 0,
          "revenue": 1,
          "type": 3,
          "typeSymbol": "-",
          "uidSectorOwner": -1,
          "x": 2,
          "y": 3
        },
        {
          "uidPlanet": 3,
          "i": 27,
          "maxPopulation": 2000,
          "population": 0,
          "revenue": 2,
          "type": 1,
          "typeSymbol": ".",
          "uidSectorOwner": -1,
          "x": 3,
          "y": 3
        },
        {
          "uidPlanet": 3,
          "i": 28,
          "maxPopulation": 800,
          "population": 0,
          "revenue": 2,
          "type": 4,
          "typeSymbol": "^",
          "uidSectorOwner": -1,
          "x": 4,
          "y": 3
        },
        {
          "uidPlanet": 3,
          "i": 29,
          "maxPopulation": 200,
          "population": 0,
          "revenue": 2,
          "type": 7,
          "typeSymbol": "x",
          "uidSectorOwner": -1,
          "x": 5,
          "y": 3
        },
        {
          "uidPlanet": 3,
          "i": 30,
          "maxPopulation": 800,
          "population": 0,
          "revenue": 2,
          "type": 4,
          "typeSymbol": "^",
          "uidSectorOwner": -1,
          "x": 6,
          "y": 3
        },
        {
          "uidPlanet": 3,
          "i": 31,
          "maxPopulation": 800,
          "population": 0,
          "revenue": 2,
          "type": 4,
          "typeSymbol": "^",
          "uidSectorOwner": -1,
          "x": 7,
          "y": 3
        }
      ],
      "type": "Airless",
      "width": 8
    },
    "4": {
      "uid": 4,
      "sid": 4,
      "uidStar": 0,
      "loc": {
        "level": 3,
        "uidRef": 0,
        "x": -31.47699,
        "y": 17.46995,
        "t": 2.6349134,
        "r": 36.0,
        "sx": -1,
        "sy": -1
      },
      "height": 4,
      "idxtype": 0,
      "landedUidShips": [],
      "name": "Skidbladnir",
      "orbitUidShips": [],
      "planetPopulation": 0,
      "planetUidRaces": [],
      "sectors": [
        {
          "uidPlanet": 4,
          "i": 0,
          "maxPopulation": 2000,
          "population": 0,
          "revenue": 2,
          "type": 1,
          "typeSymbol": ".",
          "uidSectorOwner": -1,
          "x": 0,
          "y": 0
        },
        {
          "uidPlanet": 4,
          "i": 1,
          "maxPopulation": 5000,
          "population": 0,
          "revenue": 1,
          "type": 5,
          "typeSymbol": "*",
          "uidSectorOwner": -1,
          "x": 1,
          "y": 0
        },
        {
          "uidPlanet": 4,
          "i": 2,
          "maxPopulation": 2000,
          "population": 0,
          "revenue": 2,
          "type": 1,
          "typeSymbol": ".",
          "uidSectorOwner": -1,
          "x": 2,
          "y": 0
        },
        {
          "uidPlanet": 4,
          "i": 3,
          "maxPopulation": 1000,
          "population": 0,
          "revenue": 1,
          "type": 0,
          "typeSymbol": "~",
          "uidSectorOwner": -1,
          "x": 3,
          "y": 0
        },
        {
          "uidPlanet": 4,
          "i": 4,
          "maxPopulation": 1000,
          "population": 0,
          "revenue": 1,
          "type": 0,
          "typeSymbol": "~",
          "uidSectorOwner": -1,
          "x": 4,
          "y": 0
        },
        {
          "uidPlanet": 4,
          "i": 5,
          "maxPopulation": 1000,
          "population": 0,
          "revenue": 1,
          "type": 0,
          "typeSymbol": "~",
          "uidSectorOwner": -1,
          "x": 5,
          "y": 0
        },
        {
          "uidPlanet": 4,
          "i": 6,
          "maxPopulation": 1000,
          "population": 0,
          "revenue": 1,
          "type": 0,
          "typeSymbol": "~",
          "uidSectorOwner": -1,
          "x": 6,
          "y": 0
        },
        {
          "uidPlanet": 4,
          "i": 7,
          "maxPopulation": 1000,
          "population": 0,
          "revenue": 1,
          "type": 0,
          "typeSymbol": "~",
          "uidSectorOwner": -1,
          "x": 7,
          "y": 0
        },
        {
          "uidPlanet": 4,
          "i": 8,
          "maxPopulation": 2000,
          "population": 0,
          "revenue": 2,
          "type": 1,
          "typeSymbol": ".",
          "uidSectorOwner": -1,
          "x": 0,
          "y": 1
        },
        {
          "uidPlanet": 4,
          "i": 9,
          "maxPopulation": 1000,
          "population": 0,
          "revenue": 1,
          "type": 0,
          "typeSymbol": "~",
          "uidSectorOwner": -1,
          "x": 1,
          "y": 1
        },
        {
          "uidPlanet": 4,
          "i": 10,
          "maxPopulation": 1000,
          "population": 0,
          "revenue": 1,
          "type": 0,
          "typeSymbol": "~",
          "uidSectorOwner": -1,
          "x": 2,
          "y": 1
        },
        {
          "uidPlanet": 4,
          "i": 11,
          "maxPopulation": 2000,
          "population": 0,
          "revenue": 2,
          "type": 1,
          "typeSymbol": ".",
          "uidSectorOwner": -1,
          "x": 3,
          "y": 1
        },
        {
          "uidPlanet": 4,
          "i": 12,
          "maxPopulation": 2000,
          "population": 0,
          "revenue": 2,
          "type": 1,
          "typeSymbol": ".",
          "uidSectorOwner": -1,
          "x": 4,
          "y": 1
        },
        {
          "uidPlanet": 4,
          "i": 13,
          "maxPopulation": 1000,
          "population": 0,
          "revenue": 1,
          "type": 0,
          "typeSymbol": "~",
          "uidSectorOwner": -1,
          "x": 5,
          "y": 1
        },
        {
          "uidPlanet": 4,
          "i": 14,
          "maxPopulation": 1000,
          "population": 0,
          "revenue": 1,
          "type": 0,
          "typeSymbol": "~",
          "uidSectorOwner": -1,
          "x": 6,
          "y": 1
        },
        {
          "uidPlanet": 4,
          "i": 15,
          "maxPopulation": 100,
          "population": 0,
          "revenue": 0,
          "type": 6,
          "typeSymbol": "#",
          "uidSectorOwner": -1,
          "x": 7,
          "y": 1
        },
        {
          "uidPlanet": 4,
          "i": 16,
          "maxPopulation": 1000,
          "population": 0,
          "revenue": 1,
          "type": 0,
          "typeSymbol": "~",
          "uidSectorOwner": -1,
          "x": 0,
          "y": 2
        },
        {
          "uidPlanet": 4,
          "i": 17,
          "maxPopulation": 2000,
          "population": 0,
          "revenue": 2,
          "type": 1,
          "typeSymbol": ".",
          "uidSectorOwner": -1,
          "x": 1,
          "y": 2
        },
        {
          "uidPlanet": 4,
          "i": 18,
          "maxPopulation": 2000,
          "population": 0,
          "revenue": 2,
          "type": 1,
          "typeSymbol": ".",
          "uidSectorOwner": -1,
          "x": 2,
          "y": 2
        },
        {
          "uidPlanet": 4,
          "i": 19,
          "maxPopulation": 2000,
          "population": 0,
          "revenue": 2,
          "type": 1,
          "typeSymbol": ".",
          "uidSectorOwner": -1,
          "x": 3,
          "y": 2
        },
        {
          "uidPlanet": 4,
          "i": 20,
          "maxPopulation": 1000,
          "population": 0,
          "revenue": 1,
          "type": 0,
          "typeSymbol": "~",
          "uidSectorOwner": -1,
          "x": 4,
          "y": 2
        },
        {
          "uidPlanet": 4,
          "i": 21,
          "maxPopulation": 5000,
          "population": 0,
          "revenue": 1,
          "type": 5,
          "typeSymbol": "*",
          "uidSectorOwner": -1,
          "x": 5,
          "y": 2
        },
        {
          "uidPlanet": 4,
          "i": 22,
          "maxPopulation": 2000,
          "population": 0,
          "revenue": 2,
          "type": 1,
          "typeSymbol": ".",
          "uidSectorOwner": -1,
          "x": 6,
          "y": 2
        },
        {
          "uidPlanet": 4,
          "i": 23,
          "maxPopulation": 2000,
          "population": 0,
          "revenue": 2,
          "type": 1,
          "typeSymbol": ".",
          "uidSectorOwner": -1,
          "x": 7,
          "y": 2
        },
        {
          "uidPlanet": 4,
          "i": 24,
          "maxPopulation": 1000,
          "population": 0,
          "revenue": 1,
          "type": 0,
          "typeSymbol": "~",
          "uidSectorOwner": -1,
          "x": 0,
          "y": 3
        },
        {
          "uidPlanet": 4,
          "i": 25,
          "maxPopulation": 2000,
          "population": 0,
          "revenue": 2,
          "type": 1,
          "typeSymbol": ".",
          "uidSectorOwner": -1,
          "x": 1,
          "y": 3
        },
        {
          "uidPlanet": 4,
          "i": 26,
          "maxPopulation": 5000,
          "population": 0,
          "revenue": 1,
          "type": 5,
          "typeSymbol": "*",
          "uidSectorOwner": -1,
          "x": 2,
          "y": 3
        },
        {
          "uidPlanet": 4,
          "i": 27,
          "maxPopulation": 2000,
          "population": 0,
          "revenue": 2,
          "type": 1,
          "typeSymbol": ".",
          "uidSectorOwner": -1,
          "x": 3,
          "y": 3
        },
        {
          "uidPlanet": 4,
          "i": 28,
          "maxPopulation": 2000,
          "population": 0,
          "revenue": 2,
          "type": 1,
          "typeSymbol": ".",
          "uidSectorOwner": -1,
          "x": 4,
          "y": 3
        },
        {
          "uidPlanet": 4,
          "i": 29,
          "maxPopulation": 2000,
          "population": 0,
          "revenue": 2,
          "type": 1,
          "typeSymbol": ".",
          "uidSectorOwner": -1,
          "x": 5,
          "y": 3
        },
        {
          "uidPlanet": 4,
          "i": 30,
          "maxPopulation": 2000,
          "population": 0,
          "revenue": 2,
          "type": 1,
          "typeSymbol": ".",
          "uidSectorOwner": -1,
          "x": 6,
          "y": 3
        },
        {
          "uidPlanet": 4,
          "i": 31,
          "maxPopulation": 2000,
          "population": 0,
          "revenue": 2,
          "type": 1,
          "typeSymbol": ".",
          "uidSectorOwner": -1,
          "x": 7,
          "y": 3
        }
      ],
      "type": "M Class",
      "width": 8
    }
  },
  "patrolPoints": {
    "0": {
      "uid": 0,
      "sid": 0,
      "uidStar": 0,
      "loc": {
        "level": 3,
        "uidRef": 0,
        "x": -9.878977,
        "y": 12.585937,
        "t": 2.2362754,
        "r": 16.0,
        "sx": -1,
        "sy": -1
      },
      "orbitUidShips": []
    },
    "1": {
      "uid": 1,
      "sid": 1,
      "uidStar": 0,
      "loc": {
        "level": 3,
        "uidRef": 0,
        "x": 9.878979,
        "y": -12.585936,
        "t": 5.377868,
        "r": 16.0,
        "sx": -1,
        "sy": -1
      },
      "orbitUidShips": []
    }
  },
  "races": {
    "0": {
      "idx": 0,
      "uid": 0,
      "uidHomePlanet": 0,
      "money": 50,
      "absorption": 20,
      "birthrate": 50,
      "description": "Xenos can’t burn and they can’t suffocate. They can glide at 65mph and they can run at 20 mph and they walk at 5mph. They can find underground materials fast.",
      "explore": 20,
      "name": "Xenos",
      "population": 0,
      "production": 50,
      "raceUidShips": [
        1000
      ],
      "raceVisibleStars": [
        0
      ],
      "uidHeadquarters": 1000
    }
  },
  "ships": {
    "1000": {
      "uid": 1000,
      "idxtype": 3,
      "uidRace": 0,
      "loc": {
        "level": 1,
        "uidRef": 0,
        "x": -1.0,
        "y": -1.0,
        "t": -1.0,
        "r": -1.0,
        "sx": 3,
        "sy": 1
      },
      "damage": 0,
      "guns": 0,
      "health": 1000,
      "name": "XH1000",
      "range": 0,
      "speed": 0,
      "trails": [],
      "type": "Headquarters"
    }
  },
  "shots": [],
  "news": [
    "Universe: A random universe.\n"
  ],
  "deepSpaceUidShips": []
}